[
    {
        "key": "dbln",
        "value": "%7B%2261586196522735%22%3A%22TMtP1iFW%22%2C%2261586014512854%22%3A%22UPI1o1pO%22%7D",
        "domain": "facebook.com",
        "path": "/login/device-based/",
        "hostOnly": false,
        "creation": "2026-01-26T04:23:17.553Z",
        "lastAccessed": "2026-01-26T04:23:17.555Z"
    },
    {
        "key": "sb",
        "value": "W6D5ZaK18MsLN-dGAb2G8w0b",
        "domain": "facebook.com",
        "path": "/",
        "hostOnly": false,
        "creation": "2026-01-26T04:23:17.555Z",
        "lastAccessed": "2026-01-26T04:23:17.555Z"
    },
    {
        "key": "datr",
        "value": "XaD5ZTowbUO8jeAVlmJp7On_",
        "domain": "facebook.com",
        "path": "/",
        "hostOnly": false,
        "creation": "2026-01-26T04:23:17.555Z",
        "lastAccessed": "2026-01-26T04:23:17.555Z"
    },
    {
        "key": "ps_l",
        "value": "1",
        "domain": "facebook.com",
        "path": "/",
        "hostOnly": false,
        "creation": "2026-01-26T04:23:17.555Z",
        "lastAccessed": "2026-01-26T04:23:17.555Z"
    },
    {
        "key": "ps_n",
        "value": "1",
        "domain": "facebook.com",
        "path": "/",
        "hostOnly": false,
        "creation": "2026-01-26T04:23:17.555Z",
        "lastAccessed": "2026-01-26T04:23:17.555Z"
    },
    {
        "key": "dpr",
        "value": "1.5",
        "domain": "facebook.com",
        "path": "/",
        "hostOnly": false,
        "creation": "2026-01-26T04:23:17.555Z",
        "lastAccessed": "2026-01-26T04:23:17.555Z"
    },
    {
        "key": "wd",
        "value": "1280x593",
        "domain": "facebook.com",
        "path": "/",
        "hostOnly": false,
        "creation": "2026-01-26T04:23:17.555Z",
        "lastAccessed": "2026-01-26T04:23:17.555Z"
    },
    {
        "key": "locale",
        "value": "en_GB",
        "domain": "facebook.com",
        "path": "/",
        "hostOnly": false,
        "creation": "2026-01-26T04:23:17.555Z",
        "lastAccessed": "2026-01-26T04:23:17.555Z"
    },
    {
        "key": "c_user",
        "value": "61586014512854",
        "domain": "facebook.com",
        "path": "/",
        "hostOnly": false,
        "creation": "2026-01-26T04:23:17.555Z",
        "lastAccessed": "2026-01-26T04:23:17.555Z"
    },
    {
        "key": "presence",
        "value": "C%7B%22t3%22%3A%5B%5D%2C%22utc3%22%3A1769400737081%2C%22v%22%3A1%7D",
        "domain": "facebook.com",
        "path": "/",
        "hostOnly": false,
        "creation": "2026-01-26T04:23:17.555Z",
        "lastAccessed": "2026-01-26T04:23:17.555Z"
    },
    {
        "key": "fr",
        "value": "1FFCtBGZlMdNMUobq.AWc5iBO3K96GXRL7T7crCGQ7vX_oiZbrMM3TS43x4CAusGNXZ9E.Bpduws..AAA.0.0.Bpduws.AWfrqtv-crHl7UZ1oLy8wzBVG30",
        "domain": "facebook.com",
        "path": "/",
        "hostOnly": false,
        "creation": "2026-01-26T04:23:17.555Z",
        "lastAccessed": "2026-01-26T04:23:17.555Z"
    },
    {
        "key": "xs",
        "value": "23%3AaGfzaHF9DC0mrQ%3A2%3A1769359447%3A-1%3A-1%3A%3AAcxUQ1c4w44FW_VOef7LDRzUdgwPNOs_6st0fZ23zw",
        "domain": "facebook.com",
        "path": "/",
        "hostOnly": false,
        "creation": "2026-01-26T04:23:17.555Z",
        "lastAccessed": "2026-01-26T04:23:17.555Z"
    }
]
